{
    "fluentMethods": true,
    "relationships": [],
    "fields": [
        {
            "fieldName": "name",
            "fieldType": "String"
        },
        {
            "fieldName": "key",
            "fieldType": "String"
        },
        {
            "fieldName": "itemIndex",
            "fieldType": "Integer"
        },
        {
            "fieldName": "useable",
            "fieldType": "Boolean"
        },
        {
            "fieldName": "creationDate",
            "fieldType": "ZonedDateTime"
        },
        {
            "fieldName": "creationUser",
            "fieldType": "String"
        },
        {
            "fieldName": "lastUpdateDate",
            "fieldType": "ZonedDateTime"
        },
        {
            "fieldName": "lastUpdateUser",
            "fieldType": "String"
        }
    ],
    "changelogDate": "20180423144922",
    "entityTableName": "application",
    "dto": "no",
    "pagination": "infinite-scroll",
    "service": "serviceImpl",
    "jpaMetamodelFiltering": true
}
